Metadata-Version: 1.2
Name: microbeannotator
Version: 2.0.5
Summary: A user friendly microbe genome annotation tool
Home-page: https://github.com/cruizperez/MicrobeAnnotator
Author: Carlos A. Ruiz Perez
Author-email: cruizperez3@gatech.edu
License: Artistic License 2.0
Keywords: genome annotation,protein,comparative genomics
Platform: UNKNOWN
Requires-Python: >=3.6, <=3.8
